octosql_py_native.so
octosql_py/__init__.py
octosql_py/cli.py
octosql_py/octosql_py.py
octosql_py/core/__init__.py
octosql_py/core/connection.py
octosql_py/core/octosql.py
octosql_py/core/query.py
octosql_py/core/utils.py
octosql_py/core/storage/__init__.py
octosql_py/core/storage/custom.py
octosql_py/core/storage/json.py
octosql_py/core/storage/static.py
octosql_py/core/storage/storage.py
octosql_py-0.3.0.dist-info/AUTHORS.rst
octosql_py-0.3.0.dist-info/LICENSE
octosql_py-0.3.0.dist-info/METADATA
octosql_py-0.3.0.dist-info/WHEEL
octosql_py-0.3.0.dist-info/entry_points.txt
octosql_py-0.3.0.dist-info/top_level.txt
octosql_py-0.3.0.dist-info/RECORD
